LICENCE.txt
MANIFEST.in
README.rst
setup.py
automate_wsgi/__init__.py
automate_wsgi/abstractwsgi.py
automate_wsgi.egg-info/PKG-INFO
automate_wsgi.egg-info/SOURCES.txt
automate_wsgi.egg-info/dependency_links.txt
automate_wsgi.egg-info/requires.txt
automate_wsgi.egg-info/top_level.txt